outpostcli/__init__.py
outpostcli/cli.py
outpostcli/config_utils.py
outpostcli/constants.py
outpostcli/endpoints.py
outpostcli/exceptions.py
outpostcli/finetunings.py
outpostcli/utils.py
outpostcli/lfs/__init__.py
outpostcli/lfs/commands.py
outpostcli/lfs/comms.py
outpostcli/lfs/exc.py
outpostcli/lfs/file_slice.py
outpostcli/lfs/parallel.py
outpostcli/lfs/part.py
outpostcli/lfs/types.py
outpostcli/lfs/utils.py
outpostcli/lfs/storage_class/__init__.py
outpostcli/lfs/storage_class/gcs.py
outpostcli/lfs/storage_class/s3.py
outpostcli/lfs/storage_class/utils.py
outpostcli-0.0.63.dist-info/LICENSE
outpostcli-0.0.63.dist-info/METADATA
outpostcli-0.0.63.dist-info/WHEEL
outpostcli-0.0.63.dist-info/entry_points.txt
outpostcli-0.0.63.dist-info/top_level.txt
outpostcli-0.0.63.dist-info/RECORD
