Metadata-Version: 2.1
Name: outpostcli
Version: 0.0.63
Summary: CLI for Outpost
Author: Outpost Innovations, Inc.
License: MIT License
Project-URL: homepage, https://outpost.run
Project-URL: repository, https://github.com/outposthq/cli
Requires-Python: >=3.8
License-File: LICENSE
Requires-Dist: outpostkit >=0.0.69
Requires-Dist: click
Requires-Dist: rich
Requires-Dist: requests
Requires-Dist: tenacity
Requires-Dist: hf-transfer
Provides-Extra: dev
Requires-Dist: ruff ; extra == 'dev'
Requires-Dist: black ; extra == 'dev'
